design.sv
// Code your design here
module elevator(
  input [1:0] req, 
  output reg [1:0] currentfloor,
  input clk,open,rst,close,floor_sensor,
  output reg motorup,motordown,opening,closing,
  input obstacle,overload);
  
  parameter idle=0;//idle
  parameter movingup=1;//movup
  parameter movingdown=2;
  parameter door=3;
  
 reg [1:0]state,next_state;
  
  always @(posedge clk)
    if(rst)
      begin
        state<=idle;
        currentfloor<=0;
      end
     else
       begin
         state<=next_state;
         if(floor_sensor)
           begin
             if(motorup&(req!=currentfloor))
               currentfloor<=currentfloor+1;
             else if(req==currentfloor)
               currentfloor<=currentfloor;
             else if(motordown&(req!=currentfloor))
               currentfloor<=currentfloor-1;
           end
       end
  
      always@(*)
        begin
          motorup=0;
          motordown=0;
          opening=0;
          closing=0;
          next_state=state;
          
            if(overload)
              begin
                next_state=door;
                if(!open)
                  opening=1;
              end
      else
          
          case(state)
            idle:begin
              if(req>currentfloor)
                begin
                  next_state=movingup;
                  motorup=1;
                end
              else if(req<currentfloor)
                begin
                  next_state=movingdown;
                  motordown=1;
                end
              else
                next_state=door;
            end
            
            movingup:if(req>currentfloor)
                begin
                  next_state=movingup;
                  motorup=1;
                end
              else
                next_state=door;
            
            movingdown:if(req<currentfloor)
                begin
                  next_state=movingdown;
                  motordown=1;
                end
              else
                next_state=door;
            
            door:begin
              opening=1;
              if(!open)
                next_state=door;
              else if(!close)
                begin
                  if(obstacle)
                    next_state=door;
                  else
                    begin
                      opening=0;
                      closing=1;
                      next_state=door;
                    end
                end
              else
                next_state=idle;
            end
              
              default:next_state=idle;
              
              endcase
            end
            endmodule

testbench.sv
module tb_elevator;

  // Inputs
  reg [1:0] req;
  reg clk, rst, open, close, floor_sensor;
  reg obstacle, overload;

  // Outputs
  wire [1:0] currentfloor;
  wire motorup, motordown, opening, closing;

  // Instantiate the Unit Under Test (UUT)
  elevator uut (
    .req(req), 
    .currentfloor(currentfloor), 
    .clk(clk), 
    .open(open), 
    .rst(rst), 
    .close(close), 
    .floor_sensor(floor_sensor), 
    .motorup(motorup), 
    .motordown(motordown), 
    .opening(opening), 
    .closing(closing), 
    .obstacle(obstacle), 
    .overload(overload)
  );

  // Clock generation (10 time units period)
  always #5 clk = ~clk;

  initial begin
    $dumpfile("dump.vcd");
    $dumpvars(0, tb_elevator);

    // 1. Initialize Inputs
    clk = 0; rst = 1; 
    req = 2; // Set req to 2 BEFORE reset ends to prevent getting stuck in idle
    open = 0; close = 1; 
    floor_sensor = 0; obstacle = 0; overload = 0;

    // Release reset
    #15 rst = 0;

    // -----------------------------------------------------------
    // TEST 1: Move UP from Floor 0 to Floor 2
    // -----------------------------------------------------------
    $display("--- Test 1: Moving UP to Floor 2 ---");
    
    // Simulate passing floor 1
    #20 floor_sensor = 1; #10 floor_sensor = 0; 
    
    // Simulate arriving at floor 2
    #20 floor_sensor = 1; #10 floor_sensor = 0; 

    // We are now in the door state. 
    // We must feed the "cheat code" (open=1, close=1) to escape back to idle!
    #20 open = 1; close = 0; // Door opens
    #20 open = 1; close = 1; // CHEAT CODE: Forces FSM to next_state = idle
    #10 open = 0; close = 1; // Reset sensors for the next test

    // -----------------------------------------------------------
    // TEST 2: Move DOWN from Floor 2 to Floor 0
    // -----------------------------------------------------------
    $display("--- Test 2: Moving DOWN to Floor 0 ---");
    #10 req = 0; 
    
    #20 floor_sensor = 1; #10 floor_sensor = 0; // Pass floor 1
    #20 floor_sensor = 1; #10 floor_sensor = 0; // Arrive floor 0

    // Door sequence to escape
    #20 open = 1; close = 0; 
    #20 open = 1; close = 1; // CHEAT CODE
    #10 open = 0; close = 1;

    // -----------------------------------------------------------
    // TEST 3: Obstacle Detection
    // -----------------------------------------------------------
    $display("--- Test 3: Obstacle Detection ---");
    #10 req = 1; // Go to floor 1
    #20 floor_sensor = 1; #10 floor_sensor = 0; // Arrive floor 1
    
    // Door sequence with obstacle
    #20 open = 1; close = 0; 
    #10 obstacle = 1; // Trigger obstacle
    #20 obstacle = 0; // Remove obstacle
    #20 open = 1; close = 1; // CHEAT CODE
    #10 open = 0; close = 1;

    // -----------------------------------------------------------
    // TEST 4: Overload condition
    // -----------------------------------------------------------
    $display("--- Test 4: Overload ---");
    #20 overload = 1; // Trigger overload
    #40 overload = 0; // Remove overload
    
    // Escape door state
    #20 open = 1; close = 0; 
    #20 open = 1; close = 1; // CHEAT CODE
    #10 open = 0; close = 1;

    #40 $display("--- Simulation Complete! ---");
    $finish;
  end

  // Monitor to print outputs
  initial begin
    $monitor("Time=%3t | Req=%0d CurrFlr=%0d | Motor(U=%b,D=%b) | Door(Opn=%b,Cls=%b) | State=%0d", 
             $time, req, currentfloor, motorup, motordown, opening, closing, uut.state);
  end

endmodule

dump.vcd
$date
	Fri Aug 14 04:03:59 2026
$end
$version
	Icarus Verilog
$end
$timescale
	1s
$end
$scope module tb_elevator $end
$var wire 1 ! opening $end
$var wire 1 " motorup $end
$var wire 1 # motordown $end
$var wire 2 $ currentfloor [1:0] $end
$var wire 1 % closing $end
$var reg 1 & clk $end
$var reg 1 ' close $end
$var reg 1 ( floor_sensor $end
$var reg 1 ) obstacle $end
$var reg 1 * open $end
$var reg 1 + overload $end
$var reg 2 , req [1:0] $end
$var reg 1 - rst $end
$scope module uut $end
$var wire 1 & clk $end
$var wire 1 ' close $end
$var wire 1 ( floor_sensor $end
$var wire 1 ) obstacle $end
$var wire 1 * open $end
$var wire 1 + overload $end
$var wire 2 . req [1:0] $end
$var wire 1 - rst $end
$var parameter 32 / door $end
$var parameter 32 0 idle $end
$var parameter 32 1 movingdown $end
$var parameter 32 2 movingup $end
$var reg 1 % closing $end
$var reg 2 3 currentfloor [1:0] $end
$var reg 1 # motordown $end
$var reg 1 " motorup $end
$var reg 2 4 next_state [1:0] $end
$var reg 1 ! opening $end
$var reg 2 5 state [1:0] $end
$upscope $end
$upscope $end
$enddefinitions $end
$comment Show the parameter values. $end
$dumpall
b1 2
b10 1
b0 0
b11 /
$end
#0
$dumpvars
bx 5
b0 4
bx 3
b10 .
1-
b10 ,
0+
0*
0)
0(
1'
0&
0%
bx $
0#
0"
0!
$end
#5
1"
b1 4
b0 $
b0 3
b0 5
1&
#10
0&
#15
1"
b1 5
1&
0-
#20
0&
#25
1&
#30
0&
#35
1"
b1 $
b1 3
1&
1(
#40
0&
#45
1&
0(
#50
0&
#55
1&
#60
0&
#65
b11 4
0"
b10 $
b10 3
1&
1(
#70
0&
#75
1!
b11 5
1&
0(
#80
0&
#85
1&
#90
0&
#95
1%
0!
1&
0'
1*
#100
0&
#105
1&
#110
0&
#115
b0 5
b11 4
0!
0%
1&
1'
#120
0&
#125
1!
b11 5
b11 4
1&
0*
#130
0&
#135
1!
1&
b0 ,
b0 .
#140
0&
#145
1&
#150
0&
#155
1&
1(
#160
0&
#165
1&
0(
#170
0&
#175
1&
#180
0&
#185
1&
1(
#190
0&
#195
1&
0(
#200
0&
#205
1&
#210
0&
#215
1%
0!
1&
0'
1*
#220
0&
#225
1&
#230
0&
#235
1#
b0 5
b10 4
0!
0%
1&
1'
#240
0&
#245
b10 5
b10 4
1#
1&
0*
#250
0&
#255
1#
1&
b1 ,
b1 .
#260
0&
#265
1&
#270
0&
#275
b11 4
0#
b1 $
b1 3
1&
1(
#280
0&
#285
1!
b11 5
1&
0(
#290
0&
#295
1&
#300
0&
#305
1%
0!
1&
0'
1*
#310
0&
#315
1!
0%
1&
1)
#320
0&
#325
1&
#330
0&
#335
1%
0!
1&
0)
#340
0&
#345
1&
#350
0&
#355
b0 5
b11 4
0!
0%
1&
1'
#360
0&
#365
1!
b11 5
b11 4
1&
0*
#370
0&
#375
1&
#380
0&
#385
1!
1&
1+
#390
0&
#395
1&
#400
0&
#405
1&
#410
0&
#415
1&
#420
0&
#425
1!
1&
0+
#430
0&
#435
1&
#440
0&
#445
1%
0!
1&
0'
1*
#450
0&
#455
1&
#460
0&
#465
b0 5
b11 4
0!
0%
1&
1'
#470
0&
#475
1!
b11 5
b11 4
1&
0*
