moore_model/design.sv
// Code your design here
module elevator(
  input [3:0] req, 
  input clk, open, rst, close, floor_sensor, obstacle, overload,
  output reg [1:0] currentfloor,
  output motorup, motordown, opening, closing
);

  // MOORE Machine States (5 states instead of 4)
  parameter IDLE = 0;
  parameter MOVING_UP = 1;
  parameter MOVING_DOWN = 2;
  parameter DOOR_OPENING = 3;
  parameter DOOR_CLOSING = 4;
  
  reg [2:0] state, next_state;
  reg [3:0] pending_reqs;
  
  // MOORE OUTPUTS: Strictly dependent on current state ONLY
  assign motorup  = (state == MOVING_UP);
  assign motordown = (state == MOVING_DOWN);
  assign opening  = (state == DOOR_OPENING);
  assign closing = (state == DOOR_CLOSING);
  
  // Helper logic for the SCAN algorithm
  wire req_above = (currentfloor == 0 && (pending_reqs[3] | pending_reqs[2] | pending_reqs[1])) |
                   (currentfloor == 1 && (pending_reqs[3] | pending_reqs[2])) |
                   (currentfloor == 2 && (pending_reqs[3]));

  wire req_below = (currentfloor == 3 && (pending_reqs[2] | pending_reqs[1] | pending_reqs[0])) |
                   (currentfloor == 2 && (pending_reqs[1] | pending_reqs[0])) |
                   (currentfloor == 1 && (pending_reqs[0]));
                   
  wire req_here  = pending_reqs[currentfloor];

  // Sequential Logic: State Update & Memory
  always @(posedge clk) begin
    if(rst) begin
      state <= IDLE;
      currentfloor <= 0;
      pending_reqs <= 4'b0000;
    end else begin
      state <= next_state;
      
      // Latch new requests
      pending_reqs <= pending_reqs | req;
      
      // Clear request immediately when doors start opening
      if(state == DOOR_OPENING)
        pending_reqs[currentfloor] <= 1'b0;
        
      // Update floor based on current state
      if(floor_sensor) begin
        if(state == MOVING_UP)   currentfloor <= currentfloor + 1;
        else if(state == MOVING_DOWN) currentfloor <= currentfloor - 1;
      end
    end
  end
  
  always @(*) begin
    next_state = state; 
    
    case(state)
      IDLE: begin
        if(overload || req_here) next_state = DOOR_OPENING;
        else if(req_above)   next_state = MOVING_UP;
        else if(req_below)  next_state = MOVING_DOWN;
      end
      
      MOVING_UP: begin
        if(req_here)    next_state = DOOR_OPENING;
        else if(!req_above)   next_state = IDLE;
      end
      
      MOVING_DOWN: begin
        if(req_here)    next_state = DOOR_OPENING;
        else if(!req_below)   next_state = IDLE;
      end
      
      DOOR_OPENING: begin
        if(open) begin 
          if(overload) next_state = DOOR_OPENING; // Hold open
          else   next_state = DOOR_CLOSING; // Door fully opn
        end
      end
      
      DOOR_CLOSING: begin
        if(obstacle || overload) next_state = DOOR_OPENING; // Reopen
        else if(close)    next_state = IDLE;         // Door fully closed
      end
      
      default: next_state = IDLE;
    endcase
  end
endmodule

moore_model/testbench.sv
module tb_elevator;

  reg [3:0] req;
  reg clk, rst, open, close, floor_sensor, obstacle, overload;
  wire [1:0] currentfloor;
  wire motorup, motordown, opening, closing;

  elevator uut (
    .req(req), .currentfloor(currentfloor), .clk(clk), 
    .open(open), .rst(rst), .close(close), .floor_sensor(floor_sensor), 
    .motorup(motorup), .motordown(motordown), .opening(opening), 
    .closing(closing), .obstacle(obstacle), .overload(overload)
  );

  always #5 clk = ~clk;

  initial begin
    $dumpfile("dump.vcd");
    $dumpvars(0, tb_elevator);

    clk = 0; rst = 1; req = 4'b0000;
    open = 0; close = 1; floor_sensor = 0; obstacle = 0; overload = 0;
    #15 rst = 0;

    // TEST 1: Multiple Requests (Sweep UP)
    #10 req = 4'b1010; 
    #10 req = 4'b0000; 
    #20 floor_sensor = 1; #10 floor_sensor = 0; 
    #20 open = 1; close = 0; 
    #20 open = 0; close = 1; 
    #20 floor_sensor = 1; #10 floor_sensor = 0;
    #20 floor_sensor = 1; #10 floor_sensor = 0;
    #20 open = 1; close = 0; 
    #20 open = 0; close = 1; 

    // TEST 2: Move DOWN
    #10 req = 4'b0001; 
    #10 req = 4'b0000;
    #20 floor_sensor = 1; #10 floor_sensor = 0; 
    #20 floor_sensor = 1; #10 floor_sensor = 0; 
    #20 floor_sensor = 1; #10 floor_sensor = 0; 
    #20 open = 1; close = 0; 
    #20 open = 0; close = 1; 

    // TEST 3: Obstacle Detection
    #10 req = 4'b0100; 
    #10 req = 4'b0000;
    #20 floor_sensor = 1; #10 floor_sensor = 0; 
    #20 floor_sensor = 1; #10 floor_sensor = 0; 
    #20 open = 1; close = 0; 
    #10 obstacle = 1;        
    #20 obstacle = 0;        
    #20 open = 0; close = 1; 

    // TEST 4: Overload
    #20 overload = 1; 
    #40 overload = 0; 
    #20 open = 1; close = 0; 
    #20 open = 0; close = 1; 

    #40 $finish;
  end

  initial begin
    $monitor("Time=%3t | Req=%b CurrFlr=%0d | Motor(U=%b,D=%b) | Door(Opn=%b,Cls=%b) | State=%0d | Mem=%b", 
             $time, req, currentfloor, motorup, motordown, opening, closing, uut.state, uut.pending_reqs);
  end

endmodule

moore_model/dump.vcd
$date
	Sun Aug 30 03:19:24 2026
$end
$version
	Icarus Verilog
$end
$timescale
	1s
$end
$scope module tb_elevator $end
$var wire 1 ! opening $end
$var wire 1 " motorup $end
$var wire 1 # motordown $end
$var wire 2 $ currentfloor [1:0] $end
$var wire 1 % closing $end
$var reg 1 & clk $end
$var reg 1 ' close $end
$var reg 1 ( floor_sensor $end
$var reg 1 ) obstacle $end
$var reg 1 * open $end
$var reg 1 + overload $end
$var reg 4 , req [3:0] $end
$var reg 1 - rst $end
$scope module uut $end
$var wire 1 & clk $end
$var wire 1 ' close $end
$var wire 1 ( floor_sensor $end
$var wire 1 ) obstacle $end
$var wire 1 * open $end
$var wire 1 + overload $end
$var wire 4 . req [3:0] $end
$var wire 1 / req_above $end
$var wire 1 0 req_below $end
$var wire 1 - rst $end
$var wire 1 1 req_here $end
$var wire 1 ! opening $end
$var wire 1 " motorup $end
$var wire 1 # motordown $end
$var wire 1 % closing $end
$var parameter 32 2 DOOR_CLOSING $end
$var parameter 32 3 DOOR_OPENING $end
$var parameter 32 4 IDLE $end
$var parameter 32 5 MOVING_DOWN $end
$var parameter 32 6 MOVING_UP $end
$var reg 2 7 currentfloor [1:0] $end
$var reg 3 8 next_state [2:0] $end
$var reg 4 9 pending_reqs [3:0] $end
$var reg 3 : state [2:0] $end
$upscope $end
$upscope $end
$enddefinitions $end
$comment Show the parameter values. $end
$dumpall
b1 6
b10 5
b0 4
b11 3
b100 2
$end
#0
$dumpvars
bx :
bx 9
b0 8
bx 7
x1
x0
x/
b0 .
1-
b0 ,
0+
0*
0)
0(
1'
0&
x%
bx $
x#
x"
x!
$end
#5
0/
00
01
b0 9
b0 $
b0 7
0"
0#
0!
0%
b0 :
1&
#10
0&
#15
1&
0-
#20
0&
#25
b1 8
1/
b1010 9
1&
b1010 ,
b1010 .
#30
0&
#35
1"
b1 :
1&
b0 ,
b0 .
#40
0&
#45
1&
#50
0&
#55
b11 8
11
b1 $
b1 7
1&
1(
#60
0&
#65
0"
1!
b11 :
1&
0(
#70
0&
#75
01
b1000 9
1&
#80
0&
#85
0!
1%
b100 :
b100 8
1&
0'
1*
#90
0&
#95
1&
#100
0&
#105
0%
b0 :
b1 8
1&
1'
0*
#110
0&
#115
1"
b1 :
1&
#120
0&
#125
b10 $
b10 7
1&
1(
#130
0&
#135
1&
0(
#140
0&
#145
1&
#150
0&
#155
0/
b11 8
11
b11 $
b11 7
1&
1(
#160
0&
#165
0"
1!
b11 :
1&
0(
#170
0&
#175
01
b0 9
1&
#180
0&
#185
0!
1%
b100 :
b100 8
1&
0'
1*
#190
0&
#195
1&
#200
0&
#205
0%
b0 :
b0 8
1&
1'
0*
#210
0&
#215
b10 8
10
b1 9
1&
b1 ,
b1 .
#220
0&
#225
1#
b10 :
1&
b0 ,
b0 .
#230
0&
#235
1&
#240
0&
#245
b10 $
b10 7
1&
1(
#250
0&
#255
1&
0(
#260
0&
#265
1&
#270
0&
#275
b1 $
b1 7
1&
1(
#280
0&
#285
1&
0(
#290
0&
#295
1&
#300
0&
#305
00
b11 8
11
b0 $
b0 7
1&
1(
#310
0&
#315
0#
1!
b11 :
1&
0(
#320
0&
#325
01
b0 9
1&
#330
0&
#335
0!
1%
b100 :
b100 8
1&
0'
1*
#340
0&
#345
1&
#350
0&
#355
0%
b0 :
b0 8
1&
1'
0*
#360
0&
#365
b1 8
1/
b100 9
1&
b100 ,
b100 .
#370
0&
#375
1"
b1 :
1&
b0 ,
b0 .
#380
0&
#385
1&
#390
0&
#395
b1 $
b1 7
1&
1(
#400
0&
#405
1&
0(
#410
0&
#415
1&
#420
0&
#425
0/
b11 8
11
b10 $
b10 7
1&
1(
#430
0&
#435
0"
1!
b11 :
1&
0(
#440
0&
#445
01
b0 9
1&
#450
0&
#455
0!
1%
b100 :
b100 8
1&
0'
1*
#460
0&
#465
1!
0%
b11 :
b100 8
1&
1)
#470
0&
#475
b11 8
0!
1%
b100 :
1&
#480
0&
#485
b100 8
1&
0)
#490
0&
#495
1&
#500
0&
#505
0%
b0 :
b0 8
1&
1'
0*
#510
0&
#515
1&
#520
0&
#525
1!
b11 :
b11 8
1&
1+
#530
0&
#535
1&
#540
0&
#545
1&
#550
0&
#555
1&
#560
0&
#565
1&
0+
#570
0&
#575
1&
#580
0&
#585
0!
1%
b100 :
b100 8
1&
0'
1*
#590
0&
#595
1&
#600
0&
#605
0%
b0 :
b0 8
1&
1'
0*
