melay_model/design.sv
// Code your design here
module elevator(
  input [3:0] req, 
  output reg [1:0] currentfloor,
  input clk,open,rst,close,floor_sensor,
  output reg motorup,motordown,opening,closing,
  input obstacle,overload);
  
  parameter idle=0;
  parameter movingup=1;
  parameter movingdown=2;
  parameter door=3;
  
 reg [1:0]state,next_state;
  reg [3:0] pending_reqs;
  reg door_is_closing;
  
  
  always@(*)
    begin
      motorup=0;
      motordown=0;
      opening=0;
      closing=0;
      next_state=state;
      
      if(overload)
        begin
          next_state=door;
          if(!open)
            opening=1;
        end
      else
        case(state)
          idle:begin
            if(req_here)
              next_state=door;
            else if(req_above)
              begin
                next_state=movingup;
                motorup=1;
              end
            else if(req_below)
              begin
                next_state=movingdown;
                motordown=1;
              end
          end
          
          movingup:begin
            if(req_here)
              next_state=door;
            else if(req_above)
              begin
                next_state=movingup;
                motorup=1;
              end
            else
              next_state=idle;
          end
          
          movingdown:begin
            if(req_here)
              next_state=door;
            else if(req_below)
              begin
                next_state=movingdown;
                motordown=1;
              end
            else
              next_state=idle;
          end
          
          door:begin
            if (door_is_closing) begin
              opening = 0;
              closing = 1;
              if (close)
                next_state = idle; // Door fully closed, safe to move
              else
                next_state = door;
            end else begin
              opening = 1;
              closing = 0;
              next_state = door;
            end
          end
          
          default:next_state=idle;
        endcase
    end
  
  always @(posedge clk)
    if(rst)
      begin
        state<=idle;
        currentfloor<=0;
        pending_reqs<=4'b0000;
        door_is_closing<=0;
      end
     else
       begin
         state<=next_state;
         
         pending_reqs <= pending_reqs | req;
         
         if(state == door)
           pending_reqs[currentfloor] <= 1'b0;
           
         if(floor_sensor)
           begin
             if(motorup)
               currentfloor<=currentfloor+1;
             else if(motordown)
               currentfloor<=currentfloor-1;
           end
           
         // Door direction control
         if (state != door)
           door_is_closing <= 0;
         else if (obstacle)
           door_is_closing <= 0; // Reopen instantly on obstacle
         else if (open)
           door_is_closing <= 1; // Door reached fully open, start closing
       end
  
      // Helper logic to check direction of pending requests
  wire req_above = (currentfloor == 0 && (pending_reqs[3] | pending_reqs[2] | pending_reqs[1])) |
                   (currentfloor == 1 && (pending_reqs[3] | pending_reqs[2])) |
                   (currentfloor == 2 && (pending_reqs[3]));

  wire req_below = (currentfloor == 3 && (pending_reqs[2] | pending_reqs[1] | pending_reqs[0])) |
                   (currentfloor == 2 && (pending_reqs[1] | pending_reqs[0])) |
                   (currentfloor == 1 && (pending_reqs[0]));
                   
  wire req_here  = pending_reqs[currentfloor];

  
            endmodule

melay_model/testbench.sv
module tb_elevator;

  // Inputs
  reg [3:0] req;
  reg clk, rst, open, close, floor_sensor;
  reg obstacle, overload;

  // Outputs
  wire [1:0] currentfloor;
  wire motorup, motordown, opening, closing;

  // Instantiate the Unit Under Test (UUT)
  elevator uut (
    .req(req), 
    .currentfloor(currentfloor), 
    .clk(clk), 
    .open(open), 
    .rst(rst), 
    .close(close), 
    .floor_sensor(floor_sensor), 
    .motorup(motorup), 
    .motordown(motordown), 
    .opening(opening), 
    .closing(closing), 
    .obstacle(obstacle), 
    .overload(overload)
  );

  // Clock generation (10 time units period)
  always #5 clk = ~clk;

  initial begin
    $dumpfile("dump.vcd");
    $dumpvars(0, tb_elevator);

    // 1. Initialize Inputs
    clk = 0; rst = 1; 
    req = 4'b0000;
    open = 0; close = 1; // Door starts physically closed
    floor_sensor = 0; obstacle = 0; overload = 0;

    // Release reset
    #15 rst = 0;

    // -----------------------------------------------------------
    // TEST 1: Multiple Requests (Sweep UP)
    // -----------------------------------------------------------
    $display("--- Test 1: Multiple Requests (Floors 1 and 3) ---");
    #10 req = 4'b1010; // Request Floor 1 and Floor 3 simultaneously
    #10 req = 4'b0000; // Release buttons 
    
    // Arrive at floor 1
    #20 floor_sensor = 1; #10 floor_sensor = 0; 
    
    // NEW Realistic Door Sequence at Floor 1
    #20 open = 1; close = 0; // Limit switch: Door reached fully open
    #20 open = 0; close = 1; // Limit switch: Door reached fully closed (FSM goes idle)

    // Pass floor 2
    #20 floor_sensor = 1; #10 floor_sensor = 0;

    // Arrive at floor 3
    #20 floor_sensor = 1; #10 floor_sensor = 0;

    // NEW Realistic Door Sequence at Floor 3
    #20 open = 1; close = 0; 
    #20 open = 0; close = 1; 

    // -----------------------------------------------------------
    // TEST 2: Move DOWN to Floor 0
    // -----------------------------------------------------------
    $display("--- Test 2: Moving DOWN to Floor 0 ---");
    #10 req = 4'b0001; // Request Floor 0
    #10 req = 4'b0000;
    
    #20 floor_sensor = 1; #10 floor_sensor = 0; // Pass floor 2
    #20 floor_sensor = 1; #10 floor_sensor = 0; // Pass floor 1
    #20 floor_sensor = 1; #10 floor_sensor = 0; // Arrive floor 0

    // Realistic Door Sequence at Floor 0
    #20 open = 1; close = 0; 
    #20 open = 0; close = 1; 

    // -----------------------------------------------------------
    // TEST 3: Obstacle Detection
    // -----------------------------------------------------------
    $display("--- Test 3: Obstacle Detection ---");
    #10 req = 4'b0100; // Request Floor 2
    #10 req = 4'b0000;
    
    #20 floor_sensor = 1; #10 floor_sensor = 0; // Pass floor 1
    #20 floor_sensor = 1; #10 floor_sensor = 0; // Arrive floor 2
    
    // Door sequence with an obstacle interrupting the close
    #20 open = 1; close = 0; // Door opens fully
    #10 obstacle = 1;        // Someone blocks the laser sensor
    #20 obstacle = 0;        // Obstacle clears
    #20 open = 0; close = 1; // Door finally allowed to close fully

    // -----------------------------------------------------------
    // TEST 4: Overload condition
    // -----------------------------------------------------------
    $display("--- Test 4: Overload ---");
    #20 overload = 1; // Trigger weight overload
    #40 overload = 0; // Passenger steps out
    
    // Close the door after overload clears
    #20 open = 1; close = 0; 
    #20 open = 0; close = 1; 

    #40 $display("--- Simulation Complete! ---");
    $finish;
  end

  // Monitor to print outputs
  initial begin
    $monitor("Time=%3t | Req=%b CurrFlr=%0d | Motor(U=%b,D=%b) | Door(Opn=%b,Cls=%b) | State=%0d | Mem=%b", 
             $time, req, currentfloor, motorup, motordown, opening, closing, uut.state, uut.pending_reqs);
  end

endmodule

melay_model/dump.vcd
$date
	Sun Aug 30 02:55:17 2026
$end
$version
	Icarus Verilog
$end
$timescale
	1s
$end
$scope module tb_elevator $end
$var wire 1 ! opening $end
$var wire 1 " motorup $end
$var wire 1 # motordown $end
$var wire 2 $ currentfloor [1:0] $end
$var wire 1 % closing $end
$var reg 1 & clk $end
$var reg 1 ' close $end
$var reg 1 ( floor_sensor $end
$var reg 1 ) obstacle $end
$var reg 1 * open $end
$var reg 1 + overload $end
$var reg 4 , req [3:0] $end
$var reg 1 - rst $end
$scope module uut $end
$var wire 1 & clk $end
$var wire 1 ' close $end
$var wire 1 ( floor_sensor $end
$var wire 1 ) obstacle $end
$var wire 1 * open $end
$var wire 1 + overload $end
$var wire 4 . req [3:0] $end
$var wire 1 / req_above $end
$var wire 1 0 req_below $end
$var wire 1 - rst $end
$var wire 1 1 req_here $end
$var parameter 32 2 door $end
$var parameter 32 3 idle $end
$var parameter 32 4 movingdown $end
$var parameter 32 5 movingup $end
$var reg 1 % closing $end
$var reg 2 6 currentfloor [1:0] $end
$var reg 1 7 door_is_closing $end
$var reg 1 # motordown $end
$var reg 1 " motorup $end
$var reg 2 8 next_state [1:0] $end
$var reg 1 ! opening $end
$var reg 4 9 pending_reqs [3:0] $end
$var reg 2 : state [1:0] $end
$upscope $end
$upscope $end
$enddefinitions $end
$comment Show the parameter values. $end
$dumpall
b1 5
b10 4
b0 3
b11 2
$end
#0
$dumpvars
bx :
bx 9
b0 8
x7
bx 6
x1
x0
x/
b0 .
1-
b0 ,
0+
0*
0)
0(
1'
0&
0%
bx $
0#
0"
0!
$end
#5
0/
00
07
01
b0 9
b0 $
b0 6
b0 :
1&
#10
0&
#15
1&
0-
#20
0&
#25
1"
b1 8
1/
b1010 9
1&
b1010 ,
b1010 .
#30
0&
#35
1"
b1 :
1&
b0 ,
b0 .
#40
0&
#45
1&
#50
0&
#55
b11 8
0"
11
b1 $
b1 6
1&
1(
#60
0&
#65
1!
b11 :
1&
0(
#70
0&
#75
1!
01
b1000 9
1&
#80
0&
#85
1%
17
0!
1&
0'
1*
#90
0&
#95
1&
#100
0&
#105
1"
b0 :
b1 8
0%
1&
1'
0*
#110
0&
#115
1"
07
b1 :
1&
#120
0&
#125
b10 $
b10 6
1&
1(
#130
0&
#135
1&
0(
#140
0&
#145
1&
#150
0&
#155
0/
b11 8
0"
11
b11 $
b11 6
1&
1(
#160
0&
#165
1!
b11 :
1&
0(
#170
0&
#175
1!
01
b0 9
1&
#180
0&
#185
1%
17
0!
1&
0'
1*
#190
0&
#195
1&
#200
0&
#205
b0 :
b0 8
0%
1&
1'
0*
#210
0&
#215
1#
b10 8
10
07
b1 9
1&
b1 ,
b1 .
#220
0&
#225
1#
b10 :
1&
b0 ,
b0 .
#230
0&
#235
1&
#240
0&
#245
b10 $
b10 6
1&
1(
#250
0&
#255
1&
0(
#260
0&
#265
1&
#270
0&
#275
b1 $
b1 6
1&
1(
#280
0&
#285
1&
0(
#290
0&
#295
1&
#300
0&
#305
00
b11 8
0#
11
b0 $
b0 6
1&
1(
#310
0&
#315
1!
b11 :
1&
0(
#320
0&
#325
1!
01
b0 9
1&
#330
0&
#335
1%
17
0!
1&
0'
1*
#340
0&
#345
1&
#350
0&
#355
b0 :
b0 8
0%
1&
1'
0*
#360
0&
#365
1"
b1 8
1/
07
b100 9
1&
b100 ,
b100 .
#370
0&
#375
1"
b1 :
1&
b0 ,
b0 .
#380
0&
#385
1&
#390
0&
#395
b1 $
b1 6
1&
1(
#400
0&
#405
1&
0(
#410
0&
#415
1&
#420
0&
#425
0/
b11 8
0"
11
b10 $
b10 6
1&
1(
#430
0&
#435
1!
b11 :
1&
0(
#440
0&
#445
1!
01
b0 9
1&
#450
0&
#455
1%
17
0!
1&
0'
1*
#460
0&
#465
1!
0%
07
1&
1)
#470
0&
#475
1&
#480
0&
#485
1%
0!
17
1&
0)
#490
0&
#495
1&
#500
0&
#505
b0 :
b0 8
0%
1&
1'
0*
#510
0&
#515
07
1&
#520
0&
#525
b11 :
1!
b11 8
1&
1+
#530
0&
#535
1&
#540
0&
#545
1&
#550
0&
#555
1&
#560
0&
#565
1!
1&
0+
#570
0&
#575
1&
#580
0&
#585
1%
17
0!
1&
0'
1*
#590
0&
#595
1&
#600
0&
#605
b0 :
b0 8
0%
1&
1'
0*
#610
0&
#615
07
1&
